CHANGES.rst
LICENSE
MANIFEST.in
README.rst
ddg.py
setup.py
ddg.egg-info/PKG-INFO
ddg.egg-info/SOURCES.txt
ddg.egg-info/dependency_links.txt
ddg.egg-info/entry_points.txt
ddg.egg-info/top_level.txt
duckduckgo/__init__.py
duckduckgo/duckduckgo.py