Metadata-Version: 1.1
Name: ddg
Version: 0.2.2
Summary: DuckDuckGo zero-click api for your command-line
Home-page: https://github.com/justinls/ddg
Author: Justin Shrake
Author-email: justinshrake@gmail.com
License: MIT
Platform: UNKNOWN
Classifier: Development Status :: 4 - Beta
Classifier: Environment :: Console
Classifier: License :: OSI Approved :: MIT License
Classifier: Operating System :: OS Independent
Classifier: Programming Language :: Python :: 2.6
Classifier: Programming Language :: Python :: 2.7
Classifier: Topic :: Internet :: WWW/HTTP
Classifier: Topic :: Software Development :: Libraries :: Python Modules
